odoo8_addon_help_popup_document_page-8.0.1.0.0-py3.8-nspkg.pth
odoo_addons/help_popup_document_page/README.rst
odoo_addons/help_popup_document_page/__init__.py
odoo_addons/help_popup_document_page/__openerp__.py
odoo_addons/help_popup_document_page/hooks.py
odoo_addons/help_popup_document_page/data/document_page.xml
odoo_addons/help_popup_document_page/demo/document_page.xml
odoo_addons/help_popup_document_page/models/__init__.py
odoo_addons/help_popup_document_page/models/document_page.py
odoo_addons/help_popup_document_page/models/ir_actions_act_window.py
odoo_addons/help_popup_document_page/security/res_groups.xml
odoo_addons/help_popup_document_page/static/description/icon.png
odoo_addons/help_popup_document_page/tests/__init__.py
odoo_addons/help_popup_document_page/tests/test_help_popup_document_page.py
odoo_addons/help_popup_document_page/views/document_page.xml
odoo8_addon_help_popup_document_page-8.0.1.0.0.dist-info/METADATA
odoo8_addon_help_popup_document_page-8.0.1.0.0.dist-info/WHEEL
odoo8_addon_help_popup_document_page-8.0.1.0.0.dist-info/namespace_packages.txt
odoo8_addon_help_popup_document_page-8.0.1.0.0.dist-info/top_level.txt
odoo8_addon_help_popup_document_page-8.0.1.0.0.dist-info/RECORD
